musicas_cristianas/__init__.py
musicas_cristianas/musicas.py
musicas_cristianas/utils.py
musicas_cristianas-0.1.2.dist-info/METADATA
musicas_cristianas-0.1.2.dist-info/WHEEL
musicas_cristianas-0.1.2.dist-info/top_level.txt
musicas_cristianas-0.1.2.dist-info/RECORD
