Metadata-Version: 2.1
Name: musicas_cristianas
Version: 0.1.2
Summary: Paquete para obtener datos de canciones cristianas
Home-page: https://www.youtube.com
Author: Eric Hernan Ortiz Lozano
